{
  "cellHeight": 125,
  "labels": {
    "Singleplayer": {
      "file": "label_singleplayer.png",
      "width": 599
    },
    "Multiplayer": {
      "file": "label_multiplayer.png",
      "width": 540
    },
    "Options": {
      "file": "label_options.png",
      "width": 376
    },
    "Quit": {
      "file": "label_quit.png",
      "width": 202
    },
    "Quit Game": {
      "file": "label_quit_game.png",
      "width": 505
    },
    "Realms": {
      "file": "label_realms.png",
      "width": 351
    },
    "Minecraft Realms": {
      "file": "label_minecraft_realms.png",
      "width": 838
    }
  }
}